sofacomponents/Factory.py
sofacomponents/Node.py
sofacomponents/__init__.py
sofacomponents/lib/__init__.py
sofacomponents/lib/base_component.py
sofacomponents/lib/generated_classes.py
sofacomponents/lib/get_components.py
sofacomponents/lib/parse_sofa_sources.py
sofacomponents/lib/scene.py
sofacomponents/lib/template_scene.py
sofacomponents/lib/BaseFactory/__init__.py
sofacomponents/lib/BaseFactory/AnimationLoop/ConstraintAnimationLoop.py
sofacomponents/lib/BaseFactory/AnimationLoop/DefaultAnimationLoop.py
sofacomponents/lib/BaseFactory/AnimationLoop/FreeMotionAnimationLoop.py
sofacomponents/lib/BaseFactory/AnimationLoop/MultiStepAnimationLoop.py
sofacomponents/lib/BaseFactory/AnimationLoop/MultiTagAnimationLoop.py
sofacomponents/lib/BaseFactory/AnimationLoop/__init__.py
sofacomponents/lib/BaseFactory/BehaviorModel/MouseInteractor.py
sofacomponents/lib/BaseFactory/BehaviorModel/__init__.py
sofacomponents/lib/BaseFactory/CollisionAlgorithm/BruteForceDetection.py
sofacomponents/lib/BaseFactory/CollisionAlgorithm/DefaultCollisionGroupManager.py
sofacomponents/lib/BaseFactory/CollisionAlgorithm/DefaultContactManager.py
sofacomponents/lib/BaseFactory/CollisionAlgorithm/DefaultPipeline.py
sofacomponents/lib/BaseFactory/CollisionAlgorithm/DirectSAP.py
sofacomponents/lib/BaseFactory/CollisionAlgorithm/DiscreteIntersection.py
sofacomponents/lib/BaseFactory/CollisionAlgorithm/IncrSAP.py
sofacomponents/lib/BaseFactory/CollisionAlgorithm/LMDNewProximityIntersection.py
sofacomponents/lib/BaseFactory/CollisionAlgorithm/LocalMinDistance.py
sofacomponents/lib/BaseFactory/CollisionAlgorithm/MinProximityIntersection.py
sofacomponents/lib/BaseFactory/CollisionAlgorithm/NewProximityIntersection.py
sofacomponents/lib/BaseFactory/CollisionAlgorithm/RayTraceDetection.py
sofacomponents/lib/BaseFactory/CollisionAlgorithm/RuleBasedContactManager.py
sofacomponents/lib/BaseFactory/CollisionAlgorithm/__init__.py
sofacomponents/lib/BaseFactory/CollisionModel/CapsuleCollisionModel.py
sofacomponents-0.1.17.dist-info/LICENSE
sofacomponents-0.1.17.dist-info/METADATA
sofacomponents-0.1.17.dist-info/WHEEL
sofacomponents-0.1.17.dist-info/top_level.txt
sofacomponents-0.1.17.dist-info/RECORD
