Metadata-Version: 2.1
Name: sofacomponents
Version: 0.1.17
Summary: Sofa helper to build scenes
Home-page: https://gitlab.inria.fr/gdesrues1/sofacomponents
Author: Gaetan Desrues
Author-email: gaetan.desrues@inria.fr
License: UNKNOWN
Platform: UNKNOWN
Classifier: Programming Language :: Python :: 3
Classifier: License :: OSI Approved :: MIT License
Classifier: Operating System :: OS Independent
License-File: LICENSE
